LICENSE
README.md
beancount_importer_rules-0.1.8.dist-info/METADATA
beancount_importer_rules-0.1.8.dist-info/WHEEL
beancount_importer_rules-0.1.8.dist-info/entry_points.txt
beancount_importer_rules-0.1.8.dist-info/licenses/LICENSE
beancount_importer_rules/__init__.py
beancount_importer_rules/aliase.py
beancount_importer_rules/cli.py
beancount_importer_rules/constants.py
beancount_importer_rules/data_types.py
beancount_importer_rules/engine.py
beancount_importer_rules/environment.py
beancount_importer_rules/extractor.py
beancount_importer_rules/includes.py
beancount_importer_rules/post_processor.py
beancount_importer_rules/processor/__init__.py
beancount_importer_rules/processor/filters.py
beancount_importer_rules/processor/generate_posting.py
beancount_importer_rules/processor/match_paths.py
beancount_importer_rules/processor/matchers.py
beancount_importer_rules/processor/process_imports.py
beancount_importer_rules/processor/process_includes.py
beancount_importer_rules/processor/process_transaction.py
beancount_importer_rules/processor/walk_dir.py
beancount_importer_rules/templates.py
beancount_importer_rules/utils.py
pyproject.toml
beancount_importer_rules-0.1.8.dist-info/RECORD
